dualnum-0.2.1.dist-info/METADATA
dualnum-0.2.1.dist-info/WHEEL
dualnum/__init__.py
dualnum/dualnum.abi3.so
dualnum-0.2.1.dist-info/RECORD
