Metadata-Version: 2.1
Name: dualnum
Version: 0.2.1
Summary: Python bindings for num-dual: Generalized (hyper) dual numbers for the
Keywords: mathematics,numerics,differentiation
Home-Page: https://github.com/itt-ustutt/dualnum
Author: Gernot Bauer <bauer@itt.uni-stuttgart.de>, Philipp Rehner <rehner@itt.uni-stuttgart.de>
Author-email: Gernot Bauer <bauer@itt.uni-stuttgart.de>, Philipp Rehner <rehner@itt.uni-stuttgart.de>
License: MIT OR Apache-2.0
Project-URL: Source Code, https://github.com/itt-ustutt/dualnum
